multipac_testbench/__init__.py
multipac_testbench/test_campaign.py
multipac_testbench/data/__init__.py
multipac_testbench/data/testbench_configuration.toml
multipac_testbench/data/calibration/__init__.py
multipac_testbench/data/calibration/attenuations.csv
multipac_testbench/data/calibration/rf-racks/E1_fit_calibration.csv
multipac_testbench/data/calibration/rf-racks/E2_fit_calibration.csv
multipac_testbench/data/calibration/rf-racks/E3_fit_calibration.csv
multipac_testbench/data/calibration/rf-racks/E4_fit_calibration.csv
multipac_testbench/data/calibration/rf-racks/E5_fit_calibration.csv
multipac_testbench/data/calibration/rf-racks/E6_fit_calibration.csv
multipac_testbench/data/calibration/rf-racks/E7_fit_calibration.csv
multipac_testbench/data/multipactor_tests/2025.06.19_120MHz-SWR1-4.csv
multipac_testbench/data/multipactor_tests/2025.06.20_120MHz-SWR1-10.csv
multipac_testbench/data/multipactor_tests/2025.06.20_120MHz-SWR2-9.csv
multipac_testbench/data/multipactor_tests/2025.06.20_120MHz-SWR3-8.csv
multipac_testbench/data/multipactor_tests/2025.06.20_120MHz-SWR4-7.csv
multipac_testbench/data/multipactor_tests/2025.06.20_120MHz-SWR5-6.csv
multipac_testbench/data/multipactor_tests/2025.06.20_140MHz-SWR1-14.csv
multipac_testbench/data/multipactor_tests/2025.06.20_140MHz-SWR2-13.csv
multipac_testbench/data/multipactor_tests/2025.06.20_140MHz-SWR3-12.csv
multipac_testbench/data/multipactor_tests/2025.06.20_140MHz-SWR4-11.csv
multipac_testbench/data/multipactor_tests/2025.06.20_160MHz-SWR1-15.csv
multipac_testbench/data/multipactor_tests/2025.06.20_160MHz-SWR2-16.csv
multipac_testbench/data/multipactor_tests/2025.06.20_160MHz-SWR3-17.csv
multipac_testbench/data/multipactor_tests/2025.06.20_160MHz-SWR4-18.csv
multipac_testbench/data/multipactor_tests/__init__.py
multipac_testbench/data/power_steps/__init__.py
multipac_testbench/data/power_steps/250620_120130_140MHz_SWR1_14_RAW_CSV/250620-12014973-Event_-10_dBm.csv
multipac_testbench-1.8.2.dist-info/licenses/LICENSE
multipac_testbench-1.8.2.dist-info/METADATA
multipac_testbench-1.8.2.dist-info/WHEEL
multipac_testbench-1.8.2.dist-info/top_level.txt
multipac_testbench-1.8.2.dist-info/RECORD
