Metadata-Version: 2.4
Name: multipac_testbench
Version: 1.8.2
Summary: Post-treat the data produced by the MULTIPAC test bench.
Author-email: Adrien Plaçais <placais@lpsc.in2p3.fr>
Project-URL: Documentation, https://adrienplacais.github.io/multipac_testbench/html/index.html
Project-URL: Homepage, https://github.com/AdrienPlacais/multipac_testbench
Keywords: post treatment,multipactor
Classifier: Development Status :: 3 - Alpha
Classifier: Intended Audience :: Science/Research
Classifier: License :: OSI Approved :: MIT License
Classifier: Operating System :: OS Independent
Classifier: Programming Language :: Python :: 3.12
Classifier: Topic :: Scientific/Engineering :: Physics
Requires-Python: >=3.11
License-File: LICENSE
Requires-Dist: matplotlib<4,>=3.9.1
Requires-Dist: numpy<3,>=2
Requires-Dist: openpyxl<4,>=3.1
Requires-Dist: pandas<3,>=2.2
Requires-Dist: pre-commit<5,>=4
Requires-Dist: scipy<2,>=1.15
Provides-Extra: docs
Requires-Dist: sphinx<9,>=8.1; extra == "docs"
Requires-Dist: myst-parser<5,>=4; extra == "docs"
Requires-Dist: nbsphinx<1,>=0.9.7; extra == "docs"
Requires-Dist: sphinx-autodoc-typehints<4,>=3.0.1; extra == "docs"
Requires-Dist: sphinx-rtd-theme<4,>=3; extra == "docs"
Requires-Dist: sphinx-tabs<4,>=3.4; extra == "docs"
Requires-Dist: sphinxcontrib-bibtex<3,>=2.6; extra == "docs"
Provides-Extra: notebooks
Requires-Dist: jupyter<2,>=1.1; extra == "notebooks"
Provides-Extra: test
Requires-Dist: nbconvert<8,>=7.16.6; extra == "test"
Requires-Dist: nbmake<2,>=1.5.4; extra == "test"
Requires-Dist: pytest-mock<4,>=3.14; extra == "test"
Requires-Dist: pytest<9,>=8.3.2; extra == "test"
Dynamic: license-file
